FractalGen/Ifs.py
FractalGen/__init__.py
FractalGen-1.0.dist-info/METADATA
FractalGen-1.0.dist-info/WHEEL
FractalGen-1.0.dist-info/top_level.txt
FractalGen-1.0.dist-info/RECORD
